CHANGELOG.txt
LICENCE.txt
MANIFEST.in
README.md
setup.py
ds_stack/__init__.py
ds_stack.egg-info/PKG-INFO
ds_stack.egg-info/SOURCES.txt
ds_stack.egg-info/dependency_links.txt
ds_stack.egg-info/top_level.txt