Metadata-Version: 2.1
Name: ds-stack
Version: 0.0.1
Summary: stack data structure
Home-page: 
Author: Yashas R Nair
Author-email: <yashasrnair@gmail.com>
License: MIT
Keywords: ds_stack,stack,data structure,data structure stack
Classifier: Development Status :: 5 - Production/Stable
Classifier: Intended Audience :: Education
Classifier: Operating System :: Microsoft :: Windows 
Classifier: Operating System :: MacOS :: MacOS X 
Classifier: Operating System :: Unix 
Classifier: License :: OSI Approved :: MIT License
Classifier: Programming Language :: Python :: 3
License-File: LICENCE.txt
